credstash.py
credstash-1.17.0.data/scripts/credstash.py
credstash-1.17.0.dist-info/LICENSE
credstash-1.17.0.dist-info/METADATA
credstash-1.17.0.dist-info/WHEEL
credstash-1.17.0.dist-info/entry_points.txt
credstash-1.17.0.dist-info/top_level.txt
credstash-1.17.0.dist-info/RECORD
