Metadata-Version: 2.1
Name: credstash
Version: 1.17.0
Summary: A utility for managing secrets in the cloud using AWS KMS and DynamoDB
Home-page: https://github.com/fugue/credstash
Author: Alex Schoof, Mike Lin, et al.
Author-email: mike@fugue.co
License: Apache2
Platform: UNKNOWN
Classifier: Intended Audience :: Developers
Classifier: Intended Audience :: System Administrators
Classifier: License :: OSI Approved :: Apache Software License
Requires-Dist: cryptography (>=2.1)
Requires-Dist: boto3 (>=1.1.1)
Provides-Extra: yaml
Requires-Dist: PyYAML (>=3.10) ; extra == 'yaml'
